eschr/__init__.py
eschr/pl/__init__.py
eschr/pl/_palettes.py
eschr/pl/_umap_utils.py
eschr/pl/plotting.py
eschr/readwrite/__init__.py
eschr/readwrite/read_write_utils.py
eschr/tl/__init__.py
eschr/tl/_knn_utils.py
eschr/tl/_leiden.py
eschr/tl/_prune_features.py
eschr/tl/clustering.py
eschr-1.0.1.dist-info/METADATA
eschr-1.0.1.dist-info/WHEEL
eschr-1.0.1.dist-info/licenses/LICENSE
eschr-1.0.1.dist-info/RECORD
