Metadata-Version: 2.3
Name: eschr
Version: 1.0.1
Summary: A hyperparameter-randomized ensemble approach for robust clustering across diverse datasets
Project-URL: Documentation, https://eschr.readthedocs.io/
Project-URL: Source, https://github.com/zunderlab/eschr
Project-URL: Home-page, https://github.com/zunderlab/eschr
Author: Sarah Goggin
Maintainer-email: Sarah Goggin <sg4dm@virginia.edu>
License: MIT License
License-File: LICENSE
Requires-Python: <=3.10.13,>=3.7
Requires-Dist: anndata
Requires-Dist: igraph
Requires-Dist: leidenalg
Requires-Dist: matplotlib
Requires-Dist: nmslib
Requires-Dist: numpy
Requires-Dist: pandas
Requires-Dist: scanpy
Requires-Dist: scipy
Requires-Dist: session-info
Requires-Dist: umap-learn
Requires-Dist: zarr
Provides-Extra: dev
Requires-Dist: bump2version; extra == 'dev'
Requires-Dist: pre-commit; extra == 'dev'
Requires-Dist: twine>=4.0.2; extra == 'dev'
Provides-Extra: doc
Requires-Dist: ipykernel; extra == 'doc'
Requires-Dist: ipython; extra == 'doc'
Requires-Dist: myst-nb; extra == 'doc'
Requires-Dist: sphinx-autodoc-typehints; extra == 'doc'
Requires-Dist: sphinx-book-theme>=0.3.3; extra == 'doc'
Requires-Dist: sphinx-copybutton; extra == 'doc'
Requires-Dist: sphinx>=4; extra == 'doc'
Requires-Dist: sphinxcontrib-bibtex>=1.0.0; extra == 'doc'
Provides-Extra: test
Requires-Dist: pytest; extra == 'test'
Requires-Dist: pytest-cov; extra == 'test'
